pyfing/__init__.py
pyfing/definitions.py
pyfing/enhancement.py
pyfing/frequencies.py
pyfing/orientations.py
pyfing/segmentation.py
pyfing/simple_api.py
pyfing/models/SNFEN.weights.h5
pyfing/models/SNFFE.weights.h5
pyfing/models/SNFOE.weights.h5
pyfing/models/SUFS.weights.h5
pyfing/models/__init__.py
pyfing/utils/__init__.py
pyfing/utils/drawing.py
pyfing/utils/ffe.py
pyfing/utils/foe.py
pyfing/utils/fvc_segmentation.py
pyfing/utils/notebook.py
pyfing/utils/sd27.py
pyfing-0.5.0.dist-info/LICENSE
pyfing-0.5.0.dist-info/WHEEL
pyfing-0.5.0.dist-info/METADATA
pyfing-0.5.0.dist-info/RECORD
