Metadata-Version: 2.1
Name: pyfing
Version: 0.5.0
Summary: pyfing - Fingerprint recognition in Python
Author-email: Raffaele Cappelli <raffaele.cappelli@unibo.it>
Classifier: License :: OSI Approved :: MIT License
Project-URL: Home, https://github.com/raffaele-cappelli/pyfing
